INSTALL
LICENSE
README
setup.cfg
setup.py
src/currypy/__init__.py
src/currypy.egg-info/PKG-INFO
src/currypy.egg-info/SOURCES.txt
src/currypy.egg-info/dependency_links.txt
src/currypy.egg-info/top_level.txt
test/TestCurry.py
test/__init__.py