Metadata-Version: 1.0
Name: currypy
Version: 0.1.1
Summary: pickleable partial functions
Home-page: http://code.google.com/p/currypy/
Author: michael j pan
Author-email: mikepan@gmail.com
License: New BSD
Keywords: functools partial curry pickle
Platform: All
